task_runner/__init__.py
task_runner/task_runner.py
xh_advanced_task_runner-0.1.dist-info/LICENSE
xh_advanced_task_runner-0.1.dist-info/METADATA
xh_advanced_task_runner-0.1.dist-info/WHEEL
xh_advanced_task_runner-0.1.dist-info/top_level.txt
xh_advanced_task_runner-0.1.dist-info/RECORD
