Metadata-Version: 2.1
Name: xh-advanced-task-runner
Version: 0.1
Summary: An advanced package to run tasks concurrently with retries and support for thread and process pools.
Author: HuiMob
Author-email: a1817802964@gmail.com
Classifier: Programming Language :: Python :: 3
Classifier: License :: OSI Approved :: MIT License
Requires-Python: >=3.6
License-File: LICENSE
